mcp_gateway/__init__.py
mcp_gateway/config.py
mcp_gateway/exceptions.py
mcp_gateway/proxied_mcp.py
mcp_gateway/server.py
repello_mcp_gateway-1.0.7.dist-info/METADATA
repello_mcp_gateway-1.0.7.dist-info/WHEEL
repello_mcp_gateway-1.0.7.dist-info/entry_points.txt
repello_mcp_gateway-1.0.7.dist-info/top_level.txt
repello_mcp_gateway-1.0.7.dist-info/RECORD
