Metadata-Version: 2.4
Name: repello-mcp-gateway
Version: 1.0.7
Summary: A gateway for MCP servers with Repello ARGUS integration
Author-email: Repello <naman@repello.ai>
Project-URL: Homepage, https://github.com/repello-ai/mcp-gateway
Project-URL: Repository, https://github.com/repello-ai/mcp-gateway
Keywords: mcp,model context protocol,gateway,security,repello,argus
Classifier: Development Status :: 4 - Beta
Classifier: Intended Audience :: Developers
Classifier: Programming Language :: Python
Classifier: Programming Language :: Python :: 3
Classifier: Programming Language :: Python :: 3 :: Only
Classifier: Programming Language :: Python :: 3.10
Classifier: Programming Language :: Python :: 3.11
Classifier: Programming Language :: Python :: 3.12
Classifier: Topic :: Software Development :: Libraries
Classifier: Topic :: Security
Requires-Python: >=3.10
Requires-Dist: mcp[cli]>=1.8.0
Requires-Dist: httpx
Requires-Dist: repello-argus-client>=0.2.3
Provides-Extra: dev
Requires-Dist: pytest>=7.0.0; extra == "dev"
Requires-Dist: pytest-asyncio>=0.21.0; extra == "dev"
Requires-Dist: pytest-cov>=4.1.0; extra == "dev"
Requires-Dist: respx>=0.21.0; extra == "dev"
Provides-Extra: presidio
Requires-Dist: presidio-anonymizer>=2.2.0; extra == "presidio"
Requires-Dist: presidio-analyzer>=2.2.0; extra == "presidio"
Provides-Extra: xetrack
Requires-Dist: xetrack>=0.3.4; extra == "xetrack"
